MANIFEST.in
README.rst
setup.py
odl_cfg_analysis/__init__.py
odl_cfg_analysis/analyze.py
odl_cfg_analysis/command_line.py
odl_cfg_analysis/graph_style
odl_cfg_analysis.egg-info/PKG-INFO
odl_cfg_analysis.egg-info/SOURCES.txt
odl_cfg_analysis.egg-info/dependency_links.txt
odl_cfg_analysis.egg-info/entry_points.txt
odl_cfg_analysis.egg-info/not-zip-safe
odl_cfg_analysis.egg-info/requires.txt
odl_cfg_analysis.egg-info/top_level.txt