Metadata-Version: 1.0
Name: odl-cfg-analysis
Version: 0.1
Summary: Small utility visualizing ODLs config subsystem dependencies by parsing xml based config files
Home-page: https://github.com/marosmars/odl-cfg-analysis
Author: Maros Mars
Author-email: maros.mars@gmail.com
License: Apache2
Keywords: opendaylight configuration graph analysis
Platform: UNKNOWN
